Metadata-Version: 2.1
Name: odoo13-addon-account-reporting-net-weight
Version: 13.0.1.0.1.dev3
Summary: Net Weights in the invoices analysis view
Home-page: https://github.com/OCA/account-invoice-reporting
Author: Trey,Odoo Community Association (OCA)
Author-email: support@odoo-community.org
License: AGPL-3
Platform: UNKNOWN
Classifier: Programming Language :: Python
Classifier: Framework :: Odoo
Classifier: Framework :: Odoo :: 13.0
Classifier: License :: OSI Approved :: GNU Affero General Public License v3
Classifier: Development Status :: 4 - Beta
Requires-Python: >=3.5
Requires-Dist: odoo13-addon-product-net-weight
Requires-Dist: odoo <13.1dev,>=13.0a
